seedbox/cli.py
seedbox/constants.py
seedbox/options.py
seedbox/service.py
seedbox/version.py
seedbox/__init__.py
seedbox/common/timeutil.py
seedbox/common/tools.py
seedbox/common/__init__.py
seedbox/db/admin.py
seedbox/db/api.py
seedbox/db/base.py
seedbox/db/exception.py
seedbox/db/maintenance.py
seedbox/db/models.py
seedbox/db/__init__.py
seedbox/db/sqlalchemy/api.py
seedbox/db/sqlalchemy/migration.py
seedbox/db/sqlalchemy/models.py
seedbox/db/sqlalchemy/model_util.py
seedbox/db/sqlalchemy/session.py
seedbox/db/sqlalchemy/__init__.py
seedbox/db/sqlalchemy/migrate_repo/manage.py
seedbox/db/sqlalchemy/migrate_repo/migrate.cfg
seedbox/db/sqlalchemy/migrate_repo/README
seedbox/db/sqlalchemy/migrate_repo/__init__.py
seedbox/db/sqlalchemy/migrate_repo/versions/001_initial_tables.py
seedbox/db/sqlalchemy/migrate_repo/versions/002_migrate_to_V2_of_tables.py
seedbox/db/sqlalchemy/migrate_repo/versions/003_drop_V1_tables.py
seedbox/db/sqlalchemy/migrate_repo/versions/004_alter_total_time_column_on_MediaFile.py
seedbox/db/sqlalchemy/migrate_repo/versions/__init__.py
seedbox/process/flow.py
seedbox/process/manager.py
seedbox/process/workflow.py
seedbox/process/__init__.py
seedbox/tasks/base.py
seedbox/tasks/filecopy.py
seedbox/tasks/filedelete.py
seedbox/tasks/filesync.py
seedbox/tasks/fileunrar.py
seedbox/tasks/subprocessext.py
seedbox/tasks/__init__.py
seedbox/tests/test.py
seedbox/tests/test_cli.py
seedbox/tests/test_gen_config.py
seedbox/tests/test_service.py
seedbox/tests/test_version.py
seedbox/tests/__init__.py
seedbox/tests/common/test_timeutil.py
seedbox/tests/common/test_tools.py
seedbox/tests/common/__init__.py
seedbox/tests/db/test_api.py
seedbox/tests/db/test_exception.py
seedbox/tests/db/test_maintenance.py
seedbox/tests/db/test_models.py
seedbox/tests/db/__init__.py
seedbox/tests/db/sqlalchemy/test_api.py
seedbox/tests/db/sqlalchemy/test_migration.py
seedbox/tests/db/sqlalchemy/test_models.py
SeedboxManager-2.3.17.dist-info/DESCRIPTION.rst
SeedboxManager-2.3.17.dist-info/entry_points.txt
SeedboxManager-2.3.17.dist-info/METADATA
SeedboxManager-2.3.17.dist-info/metadata.json
SeedboxManager-2.3.17.dist-info/pbr.json
SeedboxManager-2.3.17.dist-info/RECORD
SeedboxManager-2.3.17.dist-info/top_level.txt
SeedboxManager-2.3.17.dist-info/WHEEL
