Metadata-Version: 2.0
Name: SeedboxManager
Version: 2.3.17
Summary: Seedbox Task Manager
Home-page: http://shad7.github.io/seedbox
Author: shad7
Author-email: kenny.shad7@gmail.com
License: MIT
Keywords: rsync,seedbox,task,parallel
Platform: UNKNOWN
Classifier: Development Status :: 4 - Beta
Classifier: Environment :: Console
Classifier: Environment :: Other Environment
Classifier: License :: OSI Approved :: MIT License
Classifier: Operating System :: OS Independent
Classifier: Programming Language :: Python
Classifier: Programming Language :: Python :: 2
Classifier: Programming Language :: Python :: 2.7
Classifier: Programming Language :: Python :: 3
Classifier: Programming Language :: Python :: 3.4
Classifier: Programming Language :: Python :: Implementation :: PyPy
Classifier: Topic :: Internet
Classifier: Topic :: Multimedia
Classifier: Topic :: Software Development :: Libraries :: Python Modules
Classifier: Topic :: Utilities
Requires-Dist: pbr (>=1.1.1)
Requires-Dist: twine
Requires-Dist: futures
Requires-Dist: oslo.config (>=1.9.0)
Requires-Dist: lockfile
Requires-Dist: rarfile (>=2.6)
Requires-Dist: six (>=1.9.0)
Requires-Dist: sqlalchemy (>=1.0.0)
Requires-Dist: sqlalchemy-migrate
Requires-Dist: stevedore (>=1.4.0)
Requires-Dist: xworkflows
Requires-Dist: click
Requires-Dist: sandman
Requires-Dist: passlib
